hopprai/__init__.py
hopprai/py.typed
hopprai-0.0.3.dist-info/METADATA
hopprai-0.0.3.dist-info/WHEEL
hopprai-0.0.3.dist-info/RECORD
