Metadata-Version: 2.3
Name: hopprai
Version: 0.0.3
Summary: SDK for interacting with the HOPPR API
Project-URL: Homepage, https://www.hoppr.ai
License: MIT
Requires-Python: >=3.12
Requires-Dist: requests>=2.32.3
